oauth_tools/__init__.py
oauth_tools/creds.py
oauth_tools-0.0.2.dist-info/METADATA
oauth_tools-0.0.2.dist-info/WHEEL
oauth_tools-0.0.2.dist-info/top_level.txt
oauth_tools-0.0.2.dist-info/RECORD
