Metadata-Version: 2.1
Name: oauth-tools
Version: 0.0.2
Summary: An easy interface for Microsoft Office 365 Oauth Device Code authentication.
Home-page: https://github.com/GrantGMiller/oauth_tools
Author: Grant miller
Author-email: grant@grant-miller.com
License: PSF
Project-URL: Source Code, https://github.com/GrantGMiller/oauth_tools
Keywords: microsoft office 365 O365 Oauth Open Authentication Device Code flask grant miller
Platform: UNKNOWN
